crossnmut/SelectionCnM.py
crossnmut/__init__.py
crossnmut-0.0.1.dist-info/METADATA
crossnmut-0.0.1.dist-info/WHEEL
crossnmut-0.0.1.dist-info/top_level.txt
crossnmut-0.0.1.dist-info/RECORD
