Metadata-Version: 2.1
Name: crossnmut
Version: 0.0.1
Summary: Basic 2 point crossover and mutation
Home-page: UNKNOWN
Author: Bishal Bhandari
Author-email: <bishalbhaandari62@gmail.com>
License: UNKNOWN
Keywords: python,genetic algorithm,crossover,mutation
Platform: UNKNOWN
Classifier: Development Status :: 1 - Planning
Classifier: Intended Audience :: Developers
Classifier: Programming Language :: Python :: 3
Classifier: Operating System :: Unix
Classifier: Operating System :: MacOS :: MacOS X
Classifier: Operating System :: Microsoft :: Windows
Requires-Dist: random
Requires-Dist: numpy
